beetrack_uploader/__init__.py
beetrack_uploader/beetrack_uploader.py
beetrack_uploader_nkipreos-0.0.1.dist-info/LICENSE
beetrack_uploader_nkipreos-0.0.1.dist-info/METADATA
beetrack_uploader_nkipreos-0.0.1.dist-info/WHEEL
beetrack_uploader_nkipreos-0.0.1.dist-info/top_level.txt
beetrack_uploader_nkipreos-0.0.1.dist-info/RECORD
